Metadata-Version: 2.1
Name: odoo14-addon-energy-communities-api
Version: 14.0.2.1.1
Summary: API/REST endpoints for energy communities
Home-page: https://coopdevs.org
Author: Coopdevs Treball SCCL & Som Energia SCCL & SomIT
Classifier: Programming Language :: Python
Classifier: Framework :: Odoo
Classifier: Framework :: Odoo :: 14.0
Requires-Python: >=3.6
Requires-Dist: email-validator ==2.2.0
Requires-Dist: extendable-pydantic ==0.0.6
Requires-Dist: odoo14-addon-auth-jwt ==14.0.2.1.2
Requires-Dist: odoo14-addon-base-rest-auth-jwt ==14.0.1.1.0
Requires-Dist: odoo14-addon-base-rest-pydantic ==14.0.4.3.3
Requires-Dist: odoo14-addon-base-rest
Requires-Dist: odoo14-addon-component
Requires-Dist: odoo14-addon-energy-communities >=14.0.9.4.0
Requires-Dist: odoo14-addon-energy-selfconsumption >=14.0.5.2.0
Requires-Dist: odoo14-addon-pydantic ==14.0.1.1.2
Requires-Dist: odoo <14.1dev,>=14.0a
Requires-Dist: pydantic <2
